Workbook

Sheet 📊 Summary
A1: Jr Lions Lacrosse — Digital Savings Book | Financial Dashboard
A2: Selected Scenario → | C2: Base Case (500 books)
A4: SELL PRICE | B4: BOOKS SOLD | C4: GROSS REVENUE | D4: TOTAL COSTS | E4: NET PROFIT | F4: PROFIT / BOOK
A5: =Assumptions!B4 | B5: =Assumptions!B10 | C5: =Assumptions!B4*Assumptions!B10 | D5: =Assumptions!B10*Assumptions!B16 | E5: =C5-D5 | F5: =IFERROR(E5/Assumptions!B10,0)
A7: SCENARIO COMPARISON
A8: Scenario | B8: Books Sold | C8: Sell Price | D8: Gross Revenue | E8: Costs | F8: Net Profit | G8: Profit / Book | H8: YoY Δ vs 100
A9: Conservative | B9: =Scenarios!B4 | C9: =Scenarios!B3 | D9: =B9*C9 | E9: =Scenarios!B4*Scenarios!B8 | F9: =D9-E9 | G9: =IFERROR(F9/B9,0) | H9: —
A10: Base Case | B10: =Scenarios!C4 | C10: =Scenarios!C3 | D10: =B10*C10 | E10: =Scenarios!C4*Scenarios!C8 | F10: =D10-E10 | G10: =IFERROR(F10/B10,0) | H10: =F10-F9
A11: Optimistic | B11: =Scenarios!D4 | C11: =Scenarios!D3 | D11: =B11*C11 | E11: =Scenarios!D4*Scenarios!D8 | F11: =D11-E11 | G11: =IFERROR(F11/B11,0) | H11: =F11-F9
A12: Stretch Goal | B12: =Scenarios!E4 | C12: =Scenarios!E3 | D12: =B12*C12 | E12: =Scenarios!E4*Scenarios!E8 | F12: =D12-E12 | G12: =IFERROR(F12/B12,0) | H12: =F12-F9
A14: DIGITAL COST BREAKDOWN (BASE CASE) | E14: CUMULATIVE REVENUE POTENTIAL
A15: Cost Item | B15: Per Book | C15: Total (Base)
A16: Payment processing (2.9% + $0.30/book) | B16: =Assumptions!B4*0.029+0.3 | C16: =B16*Assumptions!B10
A17: Digital platform / hosting (annual) | B17: =Assumptions!B20 | C17: =B17
A18: Design (Canva or volunteer) | B18: =Assumptions!B21 | C18: =B18
A19: Social ads / promotion budget | B19: =Assumptions!B22 | C19: =B19
A20: Misc (QR, comms, email platform) | B20: =Assumptions!B23 | C20: =B20
A21: TOTAL COST PER BOOK | B21: =SUM(B16:B20) | C21: =SUM(C16:C20)

Sheet Assumptions
A1: Model Assumptions — Blue cells are inputs you can change
A2: Per financial modeling convention: BLUE TEXT = inputs | BLACK TEXT = formulas
A3: PRICING
A4: Sell Price per Book ($) | B4: 30 | D4: Recommended: $30. Adjust here to model other prices.
A5: SALES VOLUME
A6: Target Books Sold | B6: 500 | D6: Base case. Change to model scenarios.
A7: PERCEIVED VALUE
A8: Estimated in-book savings value ($) | B8: 500 | D8: Conservative estimate; actual may exceed $700+
A9: Value-to-Price ratio | B9: =B7/B4 | D9: How many times the price the buyer gets back in savings
A10: REVENUE
A11: Gross Revenue ($) | B11: =B4*B5 | D11: Sell price x books sold
A12: COSTS
A13: Payment processing per book ($) | B13: =B4*0.029+0.3 | D13: 2.9% + $0.30 (Stripe/PayPal standard rate)
A14: Processing total ($) | B14: =B12*B5 | D14: Per-book rate x books sold
A15: Digital platform / hosting annual ($) | B15: 0 | D15: Set to 0 if using Google Drive / free tools; up to $150 for dedicated platform
A16: Design cost ($) | B16: 0 | D16: Set to 0 if using Canva free + volunteer; otherwise budget $200-400
A17: Social media ad budget ($) | B17: 150 | D17: Optional paid promotion; $150 is a minimal effective budget
A18: Misc (QR, email platform, comms) ($) | B18: 50 | D18: Buffer for small expenses
A19: Total Costs ($) | B19: =B13+B14+B15+B16+B17 | D19: Sum of all costs
A20: Cost per book ($) | B20: =IFERROR(B18/B5,0) | D20: Total costs divided by books sold
A21: PROFIT
A22: Net Profit ($) | B22: =B10-B18 | D22: Gross Revenue minus Total Costs
A23: Net Profit per book ($) | B23: =IFERROR(B21/B5,0) | D23: Net profit per book sold
A24: Profit margin (%) | B24: =IFERROR(B21/B10,0) | D24: Net profit as % of revenue

Sheet Scenarios
A1: Scenario Model — All scenarios at $30 sell price
A2: Metric | B2: Conservative 100 books | C2: Base Case 500 books | D2: Optimistic 750 books | E2: Stretch 1,000 books
A3: Sell price ($) | B3: 30 | C3: 30 | D3: 30 | E3: 30
A4: Books sold | B4: 100 | C4: 500 | D4: 750 | E4: 1000
A5: Gross revenue ($) | B5: =B3*B4 | C5: =C3*C4 | D5: =D3*D4 | E5: =E3*E4
A6: Payment processing ($) | B6: =B4*B3*0.029+B4*0.3 | C6: =C4*C3*0.029+C4*0.3 | D6: =D4*D3*0.029+D4*0.3 | E6: =E4*E3*0.029+E4*0.3
A7: Platform / hosting ($) | B7: 0 | C7: 0 | D7: 100 | E7: 150
A8: Design ($) | B8: 0 | C8: 0 | D8: 0 | E8: 200
A9: Ad spend ($) | B9: 50 | C9: 150 | D9: 200 | E9: 300
A10: Misc ($) | B10: 25 | C10: 50 | D10: 75 | E10: 100
A11: Total costs ($) | B11: =SUM(B6:B9) | C11: =SUM(C6:C9) | D11: =SUM(D6:D9) | E11: =SUM(E6:E9)
A12: Net profit ($) | B12: =B5-B10 | C12: =C5-C10 | D12: =D5-D10 | E12: =E5-E10
A13: Net profit per book ($) | B13: =IFERROR(B11/B4,0) | C13: =IFERROR(C11/C4,0) | D13: =IFERROR(D11/D4,0) | E13: =IFERROR(E11/E4,0)
A14: Profit margin (%) | B14: =IFERROR(B11/B5,0) | C14: =IFERROR(C11/C5,0) | D14: =IFERROR(D11/D5,0) | E14: =IFERROR(E11/E5,0)

Sheet 📅 Timeline
A1: Jr Lions Community Savings Book — Campaign Timeline
A2: Week | B2: Date Range | C2: Phase | D2: Key Actions | E2: Owner | F2: Status
A3: 1 | B3: May 21–26 | C3: Setup | D3: Decide book name, configure payment link (Stripe/Gumroad), create social handles if needed. Build partner tracker. | E3: Program Director | F3: Not Started
A4: 2 | B4: May 27–Jun 1 | C4: Anchor Outreach | D4: Send personalized emails to Heron Glen, GolfCave, Buffalo Wild Wings, Shammy Shine. Call each by Day 4. | E4: Program Director | F4: Not Started
A5: 3 | B5: Jun 2–8 | C5: Broad Outreach | D5: Send all remaining outreach emails. Log everything in tracker. Follow up anchors. | E5: Program Director | F5: Not Started
A6: 4 | B6: Jun 9–15 | C6: Secure Commitments | D6: Convert verbal yes contacts to written confirmations. Collect exact offer language and any restrictions. | E6: Program Director | F6: Not Started
A7: 5 | B7: Jun 16–22 | C7: Content Creation | D7: Design digital coupon pages (Canva). Draft all social media posts. Set up email list. | E7: Program Director | F7: Not Started
A8: 6 | B8: Jun 23–29 | C8: Soft Launch Prep | D8: Build digital book / landing page. QR code. Test payment flow. Brief team on social strategy. | E8: Program Director | F8: Not Started
A9: 7 | B9: Jun 30–Jul 6 | C9: LAUNCH 🚀 | D9: Publish digital book. Launch social campaign. Email community list. Post partner spotlights. | E9: Program Director | F9: Not Started
A10: 8 | B10: Jul 7–20 | C10: Active Campaign | D10: Weekly social posts. Partner spotlight series. Respond to questions. Track sales daily. | E10: Program Director | F10: Not Started
A11: 9 | B11: Jul 21–Aug 3 | C11: Mid-Campaign Push | D11: Post savings stories. Share how much raised so far. Drive urgency with countdown. | E11: Program Director | F11: Not Started
A12: 10 | B12: Aug 4–17 | C12: Renewal & Push | D12: Remind community. Consider flash deal. Reach out to any partners not yet confirmed. | E12: Program Director | F12: Not Started
A13: 11 | B13: Aug 18–31 | C13: Final Stretch | D13: Last push messaging. Announce total raised milestone. Close first sales window. | E13: Program Director | F13: Not Started
A14: 12 | B14: Sep 1–7 | C14: Season Restart Push | D14: Re-launch as fall season begins. New round of social posts. Re-open sales if applicable. | E14: Program Director | F14: Not Started
